duyi_mcp_demo_java152/__init__.py
duyi_mcp_demo_java152-0.1.0.dist-info/WHEEL
duyi_mcp_demo_java152-0.1.0.dist-info/entry_points.txt
duyi_mcp_demo_java152-0.1.0.dist-info/METADATA
duyi_mcp_demo_java152-0.1.0.dist-info/RECORD
