Metadata-Version: 2.3
Name: duyi-mcp-demo-java152
Version: 0.1.0
Summary: Add your description here
Author: duyi
Author-email: duyi <1079240024@qq.com>
Requires-Dist: mcp[cli]>=1.13.1
Requires-Python: >=3.13
